{"code":"10007080-009","population":{"2018-03":{"households":"1825","population":"6123","male":"3151","female":"2972","under15":"937","be1564":"4462","up65":"724","up20":"4790","be1819":"165"},"2018-02":{"households":"1821","population":"6133","male":"3157","female":"2976","under15":"942","be1564":"4474","up65":"717","up20":"4799","be1819":"163"},"2018-01":{"households":"1820","population":"6114","male":"3149","female":"2965","under15":"939","be1564":"4459","up65":"716","up20":"4791","be1819":"160"},"2017-12":{"households":"1822","population":"6124","male":"3154","female":"2970","under15":"945","be1564":"4469","up65":"710","up20":"4798","be1819":"156"},"2017-11":{"households":"1818","population":"6120","male":"3150","female":"2970","under15":"938","be1564":"4473","up65":"709","up20":"4802","be1819":"153"},"2017-10":{"households":"1818","population":"6116","male":"3152","female":"2964","under15":"936","be1564":"4477","up65":"703","up20":"4801","be1819":"153"},"2017-09":{"households":"1812","population":"6101","male":"3142","female":"2959","under15":"927","be1564":"4474","up65":"700","up20":"4790","be1819":"157"},"2017-08":{"households":"1812","population":"6106","male":"3146","female":"2960","under15":"929","be1564":"4477","up65":"700","up20":"4798","be1819":"151"},"2017-07":{"households":"1809","population":"6104","male":"3146","female":"2958","under15":"923","be1564":"4482","up65":"699","up20":"4796","be1819":"147"},"2017-06":{"households":"1813","population":"6120","male":"3155","female":"2965","under15":"931","be1564":"4492","up65":"697","up20":"4803","be1819":"153"},"2017-05":{"households":"1816","population":"6126","male":"3161","female":"2965","under15":"934","be1564":"4497","up65":"695","up20":"4806","be1819":"153"},"2017-04":{"households":"1819","population":"6132","male":"3168","female":"2964","under15":"935","be1564":"4509","up65":"688","up20":"4801","be1819":"158"},"2017-03":{"households":"1820","population":"6124","male":"3163","female":"2961","under15":"940","be1564":"4505","up65":"679","up20":"4788","be1819":"159"},"2017-02":{"households":"1814","population":"6122","male":"3157","female":"2965","under15":"946","be1564":"4500","up65":"676","up20":"4781","be1819":"160"},"2017-01":{"households":"1813","population":"6132","male":"3165","female":"2967","under15":"948","be1564":"4509","up65":"675","up20":"4787","be1819":"161"},"2016-12":{"households":"1812","population":"6123","male":"3162","female":"2961","under15":"948","be1564":"4506","up65":"669","up20":"4776","be1819":"163"},"2016-11":{"households":"1810","population":"6117","male":"3153","female":"2964","under15":"951","be1564":"4499","up65":"667","up20":"4774","be1819":"159"},"2016-10":{"households":"1807","population":"6126","male":"3159","female":"2967","under15":"957","be1564":"4502","up65":"667","up20":"4776","be1819":"158"},"2016-09":{"households":"1808","population":"6128","male":"3166","female":"2962","under15":"962","be1564":"4500","up65":"666","up20":"4777","be1819":"158"},"2016-08":{"households":"1805","population":"6115","male":"3159","female":"2956","under15":"957","be1564":"4497","up65":"661","up20":"4772","be1819":"155"},"2016-07":{"households":"1802","population":"6110","male":"3152","female":"2958","under15":"960","be1564":"4499","up65":"651","up20":"4765","be1819":"157"},"2016-06":{"households":"1798","population":"6106","male":"3154","female":"2952","under15":"953","be1564":"4505","up65":"648","up20":"4757","be1819":"164"},"2016-05":{"households":"1798","population":"6112","male":"3157","female":"2955","under15":"959","be1564":"4508","up65":"645","up20":"4757","be1819":"160"},"2016-04":{"households":"1796","population":"6115","male":"3154","female":"2961","under15":"959","be1564":"4515","up65":"641","up20":"4756","be1819":"167"},"2016-03":{"households":"1797","population":"6115","male":"3147","female":"2968","under15":"953","be1564":"4521","up65":"641","up20":"4754","be1819":"165"},"2016-02":{"households":"1798","population":"6125","male":"3156","female":"2969","under15":"960","be1564":"4527","up65":"638","up20":"4754","be1819":"169"},"2016-01":{"households":"1798","population":"6108","male":"3152","female":"2956","under15":"954","be1564":"4524","up65":"630","up20":"4744","be1819":"165"},"2015-12":{"households":"1792","population":"6096","male":"3148","female":"2948","under15":"953","be1564":"4520","up65":"623","up20":"4731","be1819":"166"},"2015-11":{"households":"1784","population":"6082","male":"3141","female":"2941","under15":"955","be1564":"4509","up65":"618","up20":"4718","be1819":"166"},"2015-10":{"households":"1778","population":"6067","male":"3129","female":"2938","under15":"953","be1564":"4506","up65":"608","up20":"4702","be1819":"171"},"2015-09":{"households":"1783","population":"6085","male":"3138","female":"2947","under15":"963","be1564":"4521","up65":"601","up20":"4712","be1819":"165"},"2015-08":{"households":"1780","population":"6096","male":"3144","female":"2952","under15":"975","be1564":"4526","up65":"595","up20":"4710","be1819":"172"},"2015-07":{"households":"1776","population":"6086","male":"3143","female":"2943","under15":"974","be1564":"4521","up65":"591","up20":"4707","be1819":"168"},"2015-06":{"households":"1775","population":"6066","male":"3133","female":"2933","under15":"961","be1564":"4513","up65":"592","up20":"4703","be1819":"165"},"2015-05":{"households":"1777","population":"6087","male":"3146","female":"2941","under15":"968","be1564":"4527","up65":"592","up20":"4711","be1819":"168"},"2015-04":{"households":"1775","population":"6081","male":"3146","female":"2935","under15":"971","be1564":"4520","up65":"590","up20":"4707","be1819":"163"},"2015-03":{"households":"1772","population":"6084","male":"3150","female":"2934","under15":"975","be1564":"4522","up65":"587","up20":"4704","be1819":"163"},"2015-02":{"households":"1771","population":"6062","male":"3144","female":"2918","under15":"964","be1564":"4517","up65":"581","up20":"4688","be1819":"165"},"2015-01":{"households":"1773","population":"6060","male":"3145","female":"2915","under15":"967","be1564":"4512","up65":"581","up20":"4685","be1819":"160"},"2014-12":{"households":"1771","population":"6043","male":"3135","female":"2908","under15":"961","be1564":"4500","up65":"582","up20":"4679","be1819":"157"},"2014-11":{"households":"1769","population":"6048","male":"3131","female":"2917","under15":"967","be1564":"4500","up65":"581","up20":"4677","be1819":"165"},"2014-10":{"households":"1766","population":"6047","male":"3134","female":"2913","under15":"969","be1564":"4503","up65":"575","up20":"4670","be1819":"167"},"2014-09":{"households":"1765","population":"6063","male":"3135","female":"2928","under15":"984","be1564":"4513","up65":"566","up20":"4672","be1819":"167"},"2014-08":{"households":"1761","population":"6061","male":"3130","female":"2931","under15":"989","be1564":"4510","up65":"562","up20":"4660","be1819":"177"},"2014-07":{"households":"1757","population":"6041","male":"3117","female":"2924","under15":"984","be1564":"4497","up65":"560","up20":"4653","be1819":"174"},"2014-06":{"households":"1761","population":"6060","male":"3127","female":"2933","under15":"985","be1564":"4512","up65":"563","up20":"4669","be1819":"168"},"2014-05":{"households":"1758","population":"6065","male":"3128","female":"2937","under15":"995","be1564":"4505","up65":"565","up20":"4668","be1819":"169"},"2014-04":{"households":"1760","population":"6092","male":"3137","female":"2955","under15":"1007","be1564":"4519","up65":"566","up20":"4681","be1819":"163"}}}