{"code":"10016050-006","population":{"2018-02":{"households":"185","population":"618","male":"321","female":"297","under15":"115","be1564":"462","up65":"41","up20":"453","be1819":"14"},"2018-01":{"households":"185","population":"618","male":"321","female":"297","under15":"115","be1564":"462","up65":"41","up20":"453","be1819":"14"},"2017-12":{"households":"185","population":"617","male":"320","female":"297","under15":"115","be1564":"462","up65":"40","up20":"454","be1819":"14"},"2017-11":{"households":"184","population":"617","male":"320","female":"297","under15":"115","be1564":"461","up65":"41","up20":"453","be1819":"15"},"2017-10":{"households":"185","population":"615","male":"318","female":"297","under15":"114","be1564":"461","up65":"40","up20":"452","be1819":"16"},"2017-09":{"households":"185","population":"614","male":"318","female":"296","under15":"116","be1564":"459","up65":"39","up20":"451","be1819":"17"},"2017-08":{"households":"185","population":"614","male":"318","female":"296","under15":"116","be1564":"459","up65":"39","up20":"450","be1819":"16"},"2017-07":{"households":"185","population":"612","male":"317","female":"295","under15":"114","be1564":"459","up65":"39","up20":"450","be1819":"17"},"2017-06":{"households":"185","population":"612","male":"317","female":"295","under15":"115","be1564":"459","up65":"38","up20":"450","be1819":"17"},"2017-05":{"households":"185","population":"613","male":"317","female":"296","under15":"116","be1564":"459","up65":"38","up20":"450","be1819":"17"},"2017-04":{"households":"185","population":"613","male":"317","female":"296","under15":"115","be1564":"460","up65":"38","up20":"450","be1819":"19"},"2017-03":{"households":"185","population":"614","male":"317","female":"297","under15":"116","be1564":"460","up65":"38","up20":"450","be1819":"19"},"2017-02":{"households":"187","population":"613","male":"317","female":"296","under15":"113","be1564":"462","up65":"38","up20":"452","be1819":"17"},"2017-01":{"households":"187","population":"611","male":"317","female":"294","under15":"114","be1564":"459","up65":"38","up20":"452","be1819":"17"},"2016-12":{"households":"187","population":"612","male":"317","female":"295","under15":"116","be1564":"458","up65":"38","up20":"452","be1819":"17"},"2016-11":{"households":"187","population":"612","male":"316","female":"296","under15":"116","be1564":"459","up65":"37","up20":"452","be1819":"16"},"2016-10":{"households":"187","population":"609","male":"316","female":"293","under15":"117","be1564":"455","up65":"37","up20":"447","be1819":"16"},"2016-09":{"households":"187","population":"613","male":"315","female":"298","under15":"118","be1564":"459","up65":"36","up20":"449","be1819":"17"},"2016-08":{"households":"187","population":"614","male":"315","female":"299","under15":"118","be1564":"461","up65":"35","up20":"449","be1819":"17"},"2016-07":{"households":"186","population":"615","male":"316","female":"299","under15":"120","be1564":"460","up65":"35","up20":"449","be1819":"16"},"2016-06":{"households":"186","population":"614","male":"316","female":"298","under15":"120","be1564":"458","up65":"36","up20":"449","be1819":"16"},"2016-05":{"households":"186","population":"616","male":"317","female":"299","under15":"122","be1564":"458","up65":"36","up20":"450","be1819":"16"},"2016-04":{"households":"186","population":"611","male":"316","female":"295","under15":"119","be1564":"458","up65":"34","up20":"448","be1819":"16"},"2016-03":{"households":"186","population":"612","male":"317","female":"295","under15":"121","be1564":"458","up65":"33","up20":"450","be1819":"16"},"2016-02":{"households":"187","population":"612","male":"318","female":"294","under15":"119","be1564":"459","up65":"34","up20":"452","be1819":"15"},"2016-01":{"households":"187","population":"612","male":"318","female":"294","under15":"121","be1564":"458","up65":"33","up20":"451","be1819":"16"},"2015-12":{"households":"187","population":"608","male":"317","female":"291","under15":"119","be1564":"456","up65":"33","up20":"449","be1819":"18"},"2015-11":{"households":"187","population":"611","male":"319","female":"292","under15":"119","be1564":"457","up65":"35","up20":"448","be1819":"21"},"2015-10":{"households":"187","population":"609","male":"319","female":"290","under15":"119","be1564":"455","up65":"35","up20":"444","be1819":"22"},"2015-09":{"households":"187","population":"609","male":"319","female":"290","under15":"120","be1564":"454","up65":"35","up20":"443","be1819":"22"},"2015-08":{"households":"188","population":"610","male":"319","female":"291","under15":"120","be1564":"455","up65":"35","up20":"444","be1819":"22"},"2015-07":{"households":"188","population":"610","male":"319","female":"291","under15":"120","be1564":"455","up65":"35","up20":"442","be1819":"23"},"2015-06":{"households":"188","population":"609","male":"320","female":"289","under15":"120","be1564":"454","up65":"35","up20":"440","be1819":"26"},"2015-05":{"households":"189","population":"609","male":"321","female":"288","under15":"121","be1564":"452","up65":"36","up20":"438","be1819":"28"},"2015-04":{"households":"189","population":"612","male":"321","female":"291","under15":"123","be1564":"452","up65":"37","up20":"441","be1819":"26"},"2015-03":{"households":"190","population":"610","male":"319","female":"291","under15":"124","be1564":"448","up65":"38","up20":"436","be1819":"28"},"2015-02":{"households":"190","population":"610","male":"321","female":"289","under15":"123","be1564":"450","up65":"37","up20":"435","be1819":"30"},"2015-01":{"households":"190","population":"611","male":"321","female":"290","under15":"124","be1564":"450","up65":"37","up20":"434","be1819":"31"},"2014-12":{"households":"190","population":"612","male":"322","female":"290","under15":"124","be1564":"451","up65":"37","up20":"433","be1819":"32"},"2014-11":{"households":"190","population":"610","male":"318","female":"292","under15":"121","be1564":"451","up65":"38","up20":"431","be1819":"35"},"2014-10":{"households":"190","population":"609","male":"317","female":"292","under15":"120","be1564":"451","up65":"38","up20":"427","be1819":"37"},"2014-09":{"households":"190","population":"610","male":"318","female":"292","under15":"120","be1564":"453","up65":"37","up20":"428","be1819":"36"},"2014-08":{"households":"190","population":"610","male":"318","female":"292","under15":"122","be1564":"451","up65":"37","up20":"428","be1819":"35"},"2014-07":{"households":"190","population":"609","male":"317","female":"292","under15":"121","be1564":"451","up65":"37","up20":"428","be1819":"34"},"2014-06":{"households":"191","population":"609","male":"317","female":"292","under15":"120","be1564":"451","up65":"38","up20":"429","be1819":"33"},"2014-05":{"households":"192","population":"609","male":"317","female":"292","under15":"120","be1564":"451","up65":"38","up20":"428","be1819":"34"},"2014-04":{"households":"192","population":"605","male":"315","female":"290","under15":"118","be1564":"449","up65":"38","up20":"425","be1819":"35"}}}