{"code":"10018030-019","population":{"2018-03":{"households":"316","population":"962","male":"506","female":"456","under15":"161","be1564":"663","up65":"138","up20":"763","be1819":"17"},"2018-02":{"households":"314","population":"967","male":"508","female":"459","under15":"164","be1564":"665","up65":"138","up20":"765","be1819":"17"},"2018-01":{"households":"313","population":"966","male":"506","female":"460","under15":"163","be1564":"668","up65":"135","up20":"765","be1819":"15"},"2017-12":{"households":"314","population":"965","male":"507","female":"458","under15":"161","be1564":"672","up65":"132","up20":"764","be1819":"17"},"2017-11":{"households":"311","population":"965","male":"508","female":"457","under15":"161","be1564":"673","up65":"131","up20":"763","be1819":"18"},"2017-10":{"households":"312","population":"965","male":"508","female":"457","under15":"161","be1564":"672","up65":"132","up20":"764","be1819":"16"},"2017-09":{"households":"311","population":"962","male":"508","female":"454","under15":"158","be1564":"672","up65":"132","up20":"762","be1819":"17"},"2017-08":{"households":"311","population":"970","male":"512","female":"458","under15":"159","be1564":"676","up65":"135","up20":"768","be1819":"18"},"2017-07":{"households":"306","population":"964","male":"507","female":"457","under15":"158","be1564":"671","up65":"135","up20":"762","be1819":"19"},"2017-06":{"households":"306","population":"958","male":"506","female":"452","under15":"155","be1564":"668","up65":"135","up20":"757","be1819":"21"},"2017-05":{"households":"307","population":"959","male":"503","female":"456","under15":"153","be1564":"671","up65":"135","up20":"759","be1819":"21"},"2017-04":{"households":"308","population":"959","male":"504","female":"455","under15":"153","be1564":"670","up65":"136","up20":"760","be1819":"19"},"2017-03":{"households":"308","population":"963","male":"507","female":"456","under15":"152","be1564":"674","up65":"137","up20":"762","be1819":"21"},"2017-02":{"households":"310","population":"963","male":"509","female":"454","under15":"153","be1564":"673","up65":"137","up20":"762","be1819":"23"},"2017-01":{"households":"309","population":"967","male":"510","female":"457","under15":"155","be1564":"675","up65":"137","up20":"761","be1819":"26"},"2016-12":{"households":"309","population":"968","male":"507","female":"461","under15":"154","be1564":"677","up65":"137","up20":"762","be1819":"27"},"2016-11":{"households":"309","population":"969","male":"507","female":"462","under15":"155","be1564":"677","up65":"137","up20":"761","be1819":"27"},"2016-10":{"households":"309","population":"973","male":"510","female":"463","under15":"157","be1564":"678","up65":"138","up20":"764","be1819":"28"},"2016-09":{"households":"309","population":"979","male":"514","female":"465","under15":"161","be1564":"680","up65":"138","up20":"766","be1819":"26"},"2016-08":{"households":"307","population":"980","male":"514","female":"466","under15":"161","be1564":"681","up65":"138","up20":"765","be1819":"27"},"2016-07":{"households":"309","population":"981","male":"515","female":"466","under15":"161","be1564":"682","up65":"138","up20":"765","be1819":"28"},"2016-06":{"households":"308","population":"974","male":"514","female":"460","under15":"158","be1564":"679","up65":"137","up20":"762","be1819":"26"},"2016-05":{"households":"306","population":"972","male":"512","female":"460","under15":"154","be1564":"678","up65":"140","up20":"765","be1819":"25"},"2016-04":{"households":"306","population":"974","male":"515","female":"459","under15":"157","be1564":"678","up65":"139","up20":"762","be1819":"28"},"2016-03":{"households":"306","population":"970","male":"512","female":"458","under15":"157","be1564":"676","up65":"137","up20":"758","be1819":"29"},"2016-02":{"households":"307","population":"970","male":"513","female":"457","under15":"157","be1564":"677","up65":"136","up20":"758","be1819":"30"},"2016-01":{"households":"307","population":"974","male":"512","female":"462","under15":"160","be1564":"678","up65":"136","up20":"756","be1819":"33"},"2015-12":{"households":"306","population":"972","male":"511","female":"461","under15":"160","be1564":"678","up65":"134","up20":"754","be1819":"32"},"2015-11":{"households":"307","population":"977","male":"513","female":"464","under15":"163","be1564":"681","up65":"133","up20":"756","be1819":"31"},"2015-10":{"households":"307","population":"979","male":"514","female":"465","under15":"164","be1564":"681","up65":"134","up20":"758","be1819":"31"},"2015-09":{"households":"306","population":"977","male":"512","female":"465","under15":"165","be1564":"679","up65":"133","up20":"757","be1819":"29"},"2015-08":{"households":"305","population":"976","male":"512","female":"464","under15":"166","be1564":"677","up65":"133","up20":"756","be1819":"27"},"2015-07":{"households":"306","population":"976","male":"513","female":"463","under15":"167","be1564":"676","up65":"133","up20":"757","be1819":"26"},"2015-06":{"households":"305","population":"979","male":"517","female":"462","under15":"167","be1564":"679","up65":"133","up20":"758","be1819":"25"},"2015-05":{"households":"303","population":"975","male":"520","female":"455","under15":"163","be1564":"679","up65":"133","up20":"758","be1819":"24"},"2015-04":{"households":"303","population":"984","male":"525","female":"459","under15":"166","be1564":"687","up65":"131","up20":"764","be1819":"24"},"2015-03":{"households":"301","population":"981","male":"524","female":"457","under15":"162","be1564":"688","up65":"131","up20":"763","be1819":"26"},"2015-02":{"households":"300","population":"980","male":"525","female":"455","under15":"160","be1564":"689","up65":"131","up20":"764","be1819":"24"},"2015-01":{"households":"300","population":"977","male":"523","female":"454","under15":"164","be1564":"758","up65":"124","up20":"824","be1819":"18"},"2014-12":{"households":"301","population":"977","male":"523","female":"454","under15":"160","be1564":"690","up65":"127","up20":"763","be1819":"21"},"2014-11":{"households":"299","population":"968","male":"520","female":"448","under15":"154","be1564":"687","up65":"127","up20":"761","be1819":"20"},"2014-10":{"households":"299","population":"968","male":"519","female":"449","under15":"156","be1564":"686","up65":"126","up20":"758","be1819":"22"},"2014-09":{"households":"300","population":"968","male":"519","female":"449","under15":"156","be1564":"686","up65":"126","up20":"756","be1819":"25"},"2014-08":{"households":"297","population":"965","male":"516","female":"449","under15":"154","be1564":"684","up65":"127","up20":"755","be1819":"23"},"2014-07":{"households":"294","population":"960","male":"514","female":"446","under15":"154","be1564":"680","up65":"126","up20":"751","be1819":"22"},"2014-06":{"households":"293","population":"948","male":"506","female":"442","under15":"155","be1564":"666","up65":"127","up20":"737","be1819":"23"},"2014-05":{"households":"293","population":"939","male":"503","female":"436","under15":"153","be1564":"658","up65":"128","up20":"731","be1819":"24"},"2014-04":{"households":"294","population":"946","male":"504","female":"442","under15":"157","be1564":"661","up65":"128","up20":"736","be1819":"21"}},"income":{"2002":{"adm":212,"total":108867,"avg":514,"mid":418,"mid1":277,"mid3":623,"sd":368.38,"cv":71.74},"2003":{"adm":211,"total":117759,"avg":558,"mid":448,"mid1":295,"mid3":677,"sd":418.29,"cv":74.95},"2004":{"adm":223,"total":125347,"avg":562,"mid":465,"mid1":298,"mid3":680,"sd":424.6,"cv":75.54},"2005":{"adm":193,"total":121855,"avg":631,"mid":532,"mid1":320,"mid3":775,"sd":489.94,"cv":77.6},"2006":{"adm":198,"total":124250,"avg":628,"mid":482,"mid1":293,"mid3":743,"sd":573.43,"cv":91.38},"2007":{"adm":149,"total":101442,"avg":681,"mid":546,"mid1":289,"mid3":871,"sd":574.08,"cv":84.32},"2008":{"adm":191,"total":138332,"avg":724,"mid":524,"mid1":320,"mid3":866,"sd":800.02,"cv":110.46},"2009":{"adm":194,"total":125488,"avg":647,"mid":478,"mid1":269,"mid3":761,"sd":753.62,"cv":116.51},"2011":{"adm":242,"total":206844,"avg":855,"mid":566,"mid1":359,"mid3":1013,"sd":919.46,"cv":107.57},"2012":{"adm":248,"total":231197,"avg":932,"mid":620,"mid1":389,"mid3":1155,"sd":845.53,"cv":90.7},"2013":{"adm":251,"total":229568,"avg":915,"mid":602,"mid1":364,"mid3":1120,"sd":877.01,"cv":95.89},"2014":{"adm":280,"total":257572,"avg":920,"mid":621,"mid1":387,"mid3":1103,"sd":862.4,"cv":93.75},"2015":{"adm":271,"total":262860,"avg":970,"mid":615,"mid1":382,"mid3":1135,"sd":989.8,"cv":102.05},"2016":{"adm":270,"total":261305,"avg":968,"mid":626,"mid1":391,"mid3":1252,"sd":965.74,"cv":99.79},"2010":{"adm":205,"total":138746,"avg":677,"mid":487,"mid1":315,"mid3":818,"sd":766.32,"cv":113.23}}}