{"code":"10017010-011","population":{"2018-03":{"households":"629","population":"1458","male":"739","female":"719","under15":"98","be1564":"1041","up65":"319","up20":"1284","be1819":"37"},"2018-02":{"households":"629","population":"1459","male":"738","female":"721","under15":"95","be1564":"1042","up65":"322","up20":"1289","be1819":"36"},"2018-01":{"households":"630","population":"1458","male":"735","female":"723","under15":"95","be1564":"1044","up65":"319","up20":"1288","be1819":"37"},"2017-12":{"households":"636","population":"1468","male":"740","female":"728","under15":"96","be1564":"1056","up65":"316","up20":"1294","be1819":"39"},"2017-11":{"households":"640","population":"1481","male":"748","female":"733","under15":"99","be1564":"1069","up65":"313","up20":"1304","be1819":"37"},"2017-10":{"households":"638","population":"1477","male":"747","female":"730","under15":"99","be1564":"1068","up65":"310","up20":"1300","be1819":"34"},"2017-09":{"households":"638","population":"1478","male":"746","female":"732","under15":"101","be1564":"1065","up65":"312","up20":"1302","be1819":"33"},"2017-08":{"households":"635","population":"1477","male":"744","female":"733","under15":"99","be1564":"1065","up65":"313","up20":"1300","be1819":"34"},"2017-07":{"households":"635","population":"1476","male":"743","female":"733","under15":"99","be1564":"1065","up65":"312","up20":"1300","be1819":"34"},"2017-06":{"households":"634","population":"1472","male":"742","female":"730","under15":"97","be1564":"1064","up65":"311","up20":"1299","be1819":"35"},"2017-05":{"households":"636","population":"1474","male":"744","female":"730","under15":"95","be1564":"1070","up65":"309","up20":"1302","be1819":"36"},"2017-04":{"households":"640","population":"1481","male":"746","female":"735","under15":"98","be1564":"1076","up65":"307","up20":"1306","be1819":"36"},"2017-03":{"households":"642","population":"1482","male":"744","female":"738","under15":"101","be1564":"1079","up65":"302","up20":"1303","be1819":"37"},"2017-02":{"households":"642","population":"1484","male":"745","female":"739","under15":"101","be1564":"1083","up65":"300","up20":"1303","be1819":"35"},"2017-01":{"households":"644","population":"1479","male":"744","female":"735","under15":"97","be1564":"1085","up65":"297","up20":"1302","be1819":"36"},"2016-12":{"households":"642","population":"1474","male":"742","female":"732","under15":"97","be1564":"1085","up65":"292","up20":"1299","be1819":"34"},"2016-11":{"households":"642","population":"1470","male":"740","female":"730","under15":"96","be1564":"1087","up65":"287","up20":"1296","be1819":"34"},"2016-10":{"households":"642","population":"1472","male":"742","female":"730","under15":"97","be1564":"1087","up65":"288","up20":"1294","be1819":"38"},"2016-09":{"households":"641","population":"1475","male":"744","female":"731","under15":"98","be1564":"1094","up65":"283","up20":"1292","be1819":"41"},"2016-08":{"households":"638","population":"1468","male":"742","female":"726","under15":"96","be1564":"1090","up65":"282","up20":"1286","be1819":"42"},"2016-07":{"households":"635","population":"1465","male":"739","female":"726","under15":"94","be1564":"1091","up65":"280","up20":"1283","be1819":"43"},"2016-06":{"households":"638","population":"1458","male":"735","female":"723","under15":"93","be1564":"1083","up65":"282","up20":"1279","be1819":"42"},"2016-05":{"households":"637","population":"1462","male":"735","female":"727","under15":"96","be1564":"1087","up65":"279","up20":"1278","be1819":"44"},"2016-04":{"households":"635","population":"1468","male":"738","female":"730","under15":"96","be1564":"1094","up65":"278","up20":"1284","be1819":"42"},"2016-03":{"households":"637","population":"1475","male":"741","female":"734","under15":"100","be1564":"1097","up65":"278","up20":"1287","be1819":"43"},"2016-02":{"households":"636","population":"1475","male":"741","female":"734","under15":"96","be1564":"1101","up65":"278","up20":"1291","be1819":"43"},"2016-01":{"households":"635","population":"1473","male":"742","female":"731","under15":"97","be1564":"1101","up65":"275","up20":"1288","be1819":"44"},"2015-12":{"households":"635","population":"1477","male":"743","female":"734","under15":"100","be1564":"1104","up65":"273","up20":"1290","be1819":"41"},"2015-11":{"households":"634","population":"1475","male":"744","female":"731","under15":"100","be1564":"1107","up65":"268","up20":"1287","be1819":"42"},"2015-10":{"households":"633","population":"1474","male":"745","female":"729","under15":"100","be1564":"1108","up65":"266","up20":"1286","be1819":"42"},"2015-09":{"households":"633","population":"1483","male":"748","female":"735","under15":"106","be1564":"1112","up65":"265","up20":"1290","be1819":"42"},"2015-08":{"households":"635","population":"1482","male":"744","female":"738","under15":"104","be1564":"1115","up65":"263","up20":"1290","be1819":"43"},"2015-07":{"households":"635","population":"1488","male":"745","female":"743","under15":"103","be1564":"1121","up65":"264","up20":"1294","be1819":"43"},"2015-06":{"households":"635","population":"1493","male":"746","female":"747","under15":"105","be1564":"1122","up65":"266","up20":"1296","be1819":"42"},"2015-05":{"households":"634","population":"1495","male":"745","female":"750","under15":"104","be1564":"1125","up65":"266","up20":"1303","be1819":"40"},"2015-04":{"households":"632","population":"1491","male":"741","female":"750","under15":"99","be1564":"1126","up65":"266","up20":"1304","be1819":"36"},"2015-03":{"households":"636","population":"1494","male":"743","female":"751","under15":"99","be1564":"1130","up65":"265","up20":"1307","be1819":"36"},"2015-02":{"households":"635","population":"1494","male":"745","female":"749","under15":"98","be1564":"1133","up65":"263","up20":"1305","be1819":"37"},"2015-01":{"households":"634","population":"1490","male":"745","female":"745","under15":"97","be1564":"1134","up65":"259","up20":"1301","be1819":"37"},"2014-12":{"households":"632","population":"1489","male":"743","female":"746","under15":"96","be1564":"1136","up65":"257","up20":"1300","be1819":"39"},"2014-11":{"households":"633","population":"1486","male":"743","female":"743","under15":"95","be1564":"1134","up65":"257","up20":"1299","be1819":"40"},"2014-10":{"households":"635","population":"1492","male":"748","female":"744","under15":"99","be1564":"1136","up65":"257","up20":"1301","be1819":"40"},"2014-09":{"households":"635","population":"1493","male":"746","female":"747","under15":"102","be1564":"1135","up65":"256","up20":"1299","be1819":"37"},"2014-08":{"households":"633","population":"1493","male":"743","female":"750","under15":"103","be1564":"1135","up65":"255","up20":"1300","be1819":"37"},"2014-07":{"households":"630","population":"1495","male":"745","female":"750","under15":"102","be1564":"1139","up65":"254","up20":"1304","be1819":"36"},"2014-06":{"households":"629","population":"1496","male":"747","female":"749","under15":"103","be1564":"1139","up65":"254","up20":"1305","be1819":"34"},"2014-05":{"households":"631","population":"1502","male":"747","female":"755","under15":"108","be1564":"1139","up65":"255","up20":"1307","be1819":"33"},"2014-04":{"households":"628","population":"1504","male":"748","female":"756","under15":"108","be1564":"1143","up65":"253","up20":"1309","be1819":"34"}},"income":{"2002":{"adm":522,"total":325360,"avg":623,"mid":496,"mid1":301,"mid3":822,"sd":470.56,"cv":75.5},"2003":{"adm":484,"total":325473,"avg":672,"mid":523,"mid1":317,"mid3":800,"sd":878.52,"cv":130.64},"2004":{"adm":508,"total":326812,"avg":643,"mid":518,"mid1":308,"mid3":787,"sd":877.41,"cv":136.39},"2005":{"adm":490,"total":317149,"avg":647,"mid":504,"mid1":311,"mid3":767,"sd":817.76,"cv":126.34},"2006":{"adm":477,"total":318298,"avg":667,"mid":496,"mid1":346,"mid3":760,"sd":1019.52,"cv":152.78},"2007":{"adm":491,"total":334105,"avg":680,"mid":521,"mid1":338,"mid3":794,"sd":1162.34,"cv":170.82},"2008":{"adm":471,"total":361099,"avg":767,"mid":536,"mid1":348,"mid3":857,"sd":1780.5,"cv":232.24},"2009":{"adm":467,"total":316795,"avg":678,"mid":490,"mid1":313,"mid3":732,"sd":1361.57,"cv":200.71},"2011":{"adm":449,"total":347027,"avg":773,"mid":542,"mid1":329,"mid3":848,"sd":1761.12,"cv":227.86},"2012":{"adm":464,"total":386550,"avg":833,"mid":562,"mid1":371,"mid3":857,"sd":2511.15,"cv":301.43},"2013":{"adm":446,"total":366398,"avg":822,"mid":544,"mid1":343,"mid3":847,"sd":2766.18,"cv":336.72},"2014":{"adm":457,"total":395234,"avg":865,"mid":562,"mid1":341,"mid3":897,"sd":3244.85,"cv":375.19},"2015":{"adm":432,"total":386904,"avg":896,"mid":578,"mid1":360,"mid3":940,"sd":3252.02,"cv":363.11},"2016":{"adm":440,"total":387647,"avg":881,"mid":567,"mid1":345,"mid3":930,"sd":3415.8,"cv":387.71},"2010":{"adm":452,"total":340061,"avg":752,"mid":498,"mid1":317,"mid3":775,"sd":2407.27,"cv":319.97}}}