{"code":"63000010-028","population":{"2018-03":{"households":"1359","population":"3768","male":"1790","female":"1978","under15":"731","be1564":"2393","up65":"644","up20":"2849","be1819":"65"},"2018-02":{"households":"1356","population":"3756","male":"1781","female":"1975","under15":"731","be1564":"2387","up65":"638","up20":"2839","be1819":"64"},"2018-01":{"households":"1351","population":"3737","male":"1771","female":"1966","under15":"735","be1564":"2369","up65":"633","up20":"2822","be1819":"65"},"2017-12":{"households":"1355","population":"3752","male":"1777","female":"1975","under15":"745","be1564":"2380","up65":"627","up20":"2826","be1819":"68"},"2017-11":{"households":"1356","population":"3756","male":"1781","female":"1975","under15":"745","be1564":"2387","up65":"624","up20":"2826","be1819":"70"},"2017-10":{"households":"1358","population":"3760","male":"1783","female":"1977","under15":"754","be1564":"2387","up65":"619","up20":"2823","be1819":"72"},"2017-09":{"households":"1359","population":"3762","male":"1781","female":"1981","under15":"758","be1564":"2388","up65":"616","up20":"2820","be1819":"74"},"2017-08":{"households":"1359","population":"3773","male":"1788","female":"1985","under15":"759","be1564":"2399","up65":"615","up20":"2827","be1819":"70"},"2017-07":{"households":"1358","population":"3781","male":"1787","female":"1994","under15":"759","be1564":"2409","up65":"613","up20":"2833","be1819":"73"},"2017-06":{"households":"1366","population":"3809","male":"1800","female":"2009","under15":"766","be1564":"2431","up65":"612","up20":"2851","be1819":"74"},"2017-05":{"households":"1365","population":"3814","male":"1808","female":"2006","under15":"762","be1564":"2441","up65":"611","up20":"2859","be1819":"74"},"2017-04":{"households":"1362","population":"3814","male":"1810","female":"2004","under15":"759","be1564":"2441","up65":"614","up20":"2863","be1819":"75"},"2017-03":{"households":"1362","population":"3810","male":"1810","female":"2000","under15":"761","be1564":"2436","up65":"613","up20":"2861","be1819":"74"},"2017-02":{"households":"1356","population":"3796","male":"1800","female":"1996","under15":"760","be1564":"2425","up65":"611","up20":"2847","be1819":"74"},"2017-01":{"households":"1354","population":"3787","male":"1797","female":"1990","under15":"758","be1564":"2422","up65":"607","up20":"2838","be1819":"72"},"2016-12":{"households":"1355","population":"3802","male":"1804","female":"1998","under15":"770","be1564":"2430","up65":"602","up20":"2846","be1819":"72"},"2016-11":{"households":"1354","population":"3797","male":"1805","female":"1992","under15":"765","be1564":"2434","up65":"598","up20":"2840","be1819":"74"},"2016-10":{"households":"1346","population":"3796","male":"1807","female":"1989","under15":"762","be1564":"2437","up65":"597","up20":"2835","be1819":"79"},"2016-09":{"households":"1344","population":"3790","male":"1806","female":"1984","under15":"761","be1564":"2437","up65":"592","up20":"2831","be1819":"79"},"2016-08":{"households":"1350","population":"3815","male":"1820","female":"1995","under15":"777","be1564":"2449","up65":"589","up20":"2838","be1819":"83"},"2016-07":{"households":"1349","population":"3831","male":"1835","female":"1996","under15":"780","be1564":"2462","up65":"589","up20":"2842","be1819":"86"},"2016-06":{"households":"1348","population":"3826","male":"1830","female":"1996","under15":"779","be1564":"2463","up65":"584","up20":"2836","be1819":"86"},"2016-05":{"households":"1352","population":"3828","male":"1832","female":"1996","under15":"779","be1564":"2472","up65":"577","up20":"2833","be1819":"88"},"2016-04":{"households":"1358","population":"3842","male":"1836","female":"2006","under15":"789","be1564":"2480","up65":"573","up20":"2839","be1819":"86"},"2016-03":{"households":"1355","population":"3835","male":"1839","female":"1996","under15":"782","be1564":"2482","up65":"571","up20":"2841","be1819":"86"},"2016-02":{"households":"1354","population":"3846","male":"1844","female":"2002","under15":"788","be1564":"2491","up65":"567","up20":"2845","be1819":"85"},"2016-01":{"households":"1358","population":"3835","male":"1837","female":"1998","under15":"783","be1564":"2490","up65":"562","up20":"2841","be1819":"84"},"2015-12":{"households":"1364","population":"3848","male":"1843","female":"2005","under15":"787","be1564":"2502","up65":"559","up20":"2850","be1819":"81"},"2015-11":{"households":"1363","population":"3838","male":"1838","female":"2000","under15":"782","be1564":"2500","up65":"556","up20":"2843","be1819":"83"},"2015-10":{"households":"1360","population":"3837","male":"1838","female":"1999","under15":"780","be1564":"2504","up65":"553","up20":"2841","be1819":"86"},"2015-09":{"households":"1356","population":"3823","male":"1831","female":"1992","under15":"773","be1564":"2504","up65":"546","up20":"2831","be1819":"84"},"2015-08":{"households":"1359","population":"3852","male":"1848","female":"2004","under15":"784","be1564":"2524","up65":"544","up20":"2849","be1819":"85"},"2015-07":{"households":"1361","population":"3860","male":"1848","female":"2012","under15":"787","be1564":"2534","up65":"539","up20":"2856","be1819":"85"},"2015-06":{"households":"1356","population":"3862","male":"1848","female":"2014","under15":"792","be1564":"2536","up65":"534","up20":"2856","be1819":"81"},"2015-05":{"households":"1349","population":"3853","male":"1844","female":"2009","under15":"788","be1564":"2532","up65":"533","up20":"2850","be1819":"81"},"2015-04":{"households":"1350","population":"3866","male":"1851","female":"2015","under15":"791","be1564":"2545","up65":"530","up20":"2857","be1819":"82"},"2015-03":{"households":"1342","population":"3859","male":"1846","female":"2013","under15":"795","be1564":"2538","up65":"526","up20":"2854","be1819":"82"},"2015-02":{"households":"1338","population":"3854","male":"1840","female":"2014","under15":"790","be1564":"2540","up65":"524","up20":"2853","be1819":"78"},"2015-01":{"households":"1333","population":"3845","male":"1837","female":"2008","under15":"786","be1564":"2536","up65":"523","up20":"2840","be1819":"82"},"2014-12":{"households":"1332","population":"3840","male":"1836","female":"2004","under15":"792","be1564":"2531","up65":"517","up20":"2831","be1819":"83"},"2014-11":{"households":"1328","population":"3815","male":"1825","female":"1990","under15":"783","be1564":"2519","up65":"513","up20":"2811","be1819":"84"},"2014-10":{"households":"1326","population":"3801","male":"1818","female":"1983","under15":"779","be1564":"2509","up65":"513","up20":"2804","be1819":"78"},"2014-09":{"households":"1328","population":"3803","male":"1817","female":"1986","under15":"780","be1564":"2510","up65":"513","up20":"2803","be1819":"81"},"2014-08":{"households":"1331","population":"3818","male":"1830","female":"1988","under15":"785","be1564":"2525","up65":"508","up20":"2817","be1819":"79"},"2014-07":{"households":"1331","population":"3816","male":"1829","female":"1987","under15":"777","be1564":"2536","up65":"503","up20":"2819","be1819":"77"},"2014-06":{"households":"1336","population":"3811","male":"1822","female":"1989","under15":"777","be1564":"2537","up65":"497","up20":"2815","be1819":"76"},"2014-05":{"households":"1337","population":"3804","male":"1814","female":"1990","under15":"771","be1564":"2537","up65":"496","up20":"2808","be1819":"76"},"2014-04":{"households":"1340","population":"3836","male":"1822","female":"2014","under15":"779","be1564":"2563","up65":"494","up20":"2828","be1819":"79"}}}