{"code":"64000130-004","population":{"2014-04":{"households":"1031","population":"3196","male":"1658","female":"1538","under15":"377","be1564":"2469","up65":"350","up20":"2575","be1819":"100"},"2014-05":{"households":"1027","population":"3188","male":"1655","female":"1533","under15":"376","be1564":"2460","up65":"352","up20":"2570","be1819":"102"},"2014-06":{"households":"1029","population":"3204","male":"1662","female":"1542","under15":"382","be1564":"2463","up65":"359","up20":"2578","be1819":"104"},"2014-07":{"households":"1029","population":"3205","male":"1661","female":"1544","under15":"376","be1564":"2467","up65":"362","up20":"2587","be1819":"103"},"2014-08":{"households":"1027","population":"3204","male":"1662","female":"1542","under15":"370","be1564":"2471","up65":"363","up20":"2585","be1819":"104"},"2014-09":{"households":"1027","population":"3203","male":"1661","female":"1542","under15":"370","be1564":"2469","up65":"364","up20":"2586","be1819":"104"},"2014-10":{"households":"1028","population":"3209","male":"1667","female":"1542","under15":"371","be1564":"2474","up65":"364","up20":"2597","be1819":"100"},"2014-11":{"households":"1029","population":"3210","male":"1665","female":"1545","under15":"367","be1564":"2479","up65":"364","up20":"2601","be1819":"96"},"2014-12":{"households":"1030","population":"3221","male":"1668","female":"1553","under15":"370","be1564":"2489","up65":"362","up20":"2609","be1819":"95"},"2015-01":{"households":"1030","population":"3212","male":"1664","female":"1548","under15":"367","be1564":"2480","up65":"365","up20":"2600","be1819":"100"},"2015-02":{"households":"1033","population":"3223","male":"1667","female":"1556","under15":"368","be1564":"2488","up65":"367","up20":"2607","be1819":"105"},"2015-03":{"households":"1034","population":"3226","male":"1669","female":"1557","under15":"361","be1564":"2496","up65":"369","up20":"2616","be1819":"104"},"2015-04":{"households":"1031","population":"3224","male":"1664","female":"1560","under15":"360","be1564":"2499","up65":"365","up20":"2614","be1819":"104"},"2015-05":{"households":"1030","population":"3217","male":"1658","female":"1559","under15":"355","be1564":"2500","up65":"362","up20":"2609","be1819":"104"},"2015-06":{"households":"1029","population":"3213","male":"1655","female":"1558","under15":"352","be1564":"2499","up65":"362","up20":"2606","be1819":"109"},"2015-07":{"households":"1031","population":"3223","male":"1660","female":"1563","under15":"355","be1564":"2506","up65":"362","up20":"2614","be1819":"110"},"2015-08":{"households":"1028","population":"3211","male":"1649","female":"1562","under15":"352","be1564":"2499","up65":"360","up20":"2612","be1819":"104"},"2015-09":{"households":"1028","population":"3200","male":"1641","female":"1559","under15":"341","be1564":"2499","up65":"360","up20":"2608","be1819":"104"},"2015-10":{"households":"1031","population":"3206","male":"1642","female":"1564","under15":"344","be1564":"2501","up65":"361","up20":"2612","be1819":"104"},"2015-11":{"households":"1031","population":"3205","male":"1646","female":"1559","under15":"340","be1564":"2501","up65":"364","up20":"2616","be1819":"100"},"2015-12":{"households":"1032","population":"3209","male":"1648","female":"1561","under15":"341","be1564":"2506","up65":"362","up20":"2616","be1819":"100"},"2016-01":{"households":"1035","population":"3223","male":"1660","female":"1563","under15":"344","be1564":"2516","up65":"363","up20":"2627","be1819":"96"},"2016-02":{"households":"1035","population":"3224","male":"1661","female":"1563","under15":"347","be1564":"2515","up65":"362","up20":"2630","be1819":"95"},"2016-03":{"households":"1039","population":"3225","male":"1660","female":"1565","under15":"350","be1564":"2512","up65":"363","up20":"2630","be1819":"91"},"2016-04":{"households":"1039","population":"3217","male":"1653","female":"1564","under15":"346","be1564":"2507","up65":"364","up20":"2624","be1819":"94"},"2016-05":{"households":"1039","population":"3219","male":"1653","female":"1566","under15":"345","be1564":"2512","up65":"362","up20":"2628","be1819":"93"},"2016-06":{"households":"1039","population":"3219","male":"1648","female":"1571","under15":"346","be1564":"2512","up65":"361","up20":"2627","be1819":"94"},"2016-07":{"households":"1041","population":"3208","male":"1644","female":"1564","under15":"342","be1564":"2503","up65":"363","up20":"2624","be1819":"94"},"2016-08":{"households":"1040","population":"3210","male":"1644","female":"1566","under15":"345","be1564":"2501","up65":"364","up20":"2621","be1819":"95"},"2016-09":{"households":"1038","population":"3201","male":"1643","female":"1558","under15":"339","be1564":"2496","up65":"366","up20":"2615","be1819":"93"},"2016-10":{"households":"1036","population":"3209","male":"1641","female":"1568","under15":"343","be1564":"2498","up65":"368","up20":"2622","be1819":"94"},"2016-11":{"households":"1037","population":"3215","male":"1641","female":"1574","under15":"347","be1564":"2497","up65":"371","up20":"2624","be1819":"94"},"2016-12":{"households":"1039","population":"3219","male":"1641","female":"1578","under15":"348","be1564":"2499","up65":"372","up20":"2625","be1819":"99"},"2017-01":{"households":"1039","population":"3217","male":"1639","female":"1578","under15":"349","be1564":"2496","up65":"372","up20":"2628","be1819":"93"},"2017-02":{"households":"1039","population":"3214","male":"1636","female":"1578","under15":"350","be1564":"2483","up65":"381","up20":"2628","be1819":"92"},"2017-03":{"households":"1042","population":"3209","male":"1631","female":"1578","under15":"351","be1564":"2476","up65":"382","up20":"2627","be1819":"87"},"2017-04":{"households":"1042","population":"3208","male":"1627","female":"1581","under15":"347","be1564":"2478","up65":"383","up20":"2633","be1819":"89"},"2017-05":{"households":"1043","population":"3209","male":"1628","female":"1581","under15":"341","be1564":"2481","up65":"387","up20":"2644","be1819":"87"},"2017-06":{"households":"1046","population":"3213","male":"1630","female":"1583","under15":"342","be1564":"2481","up65":"390","up20":"2649","be1819":"83"},"2017-07":{"households":"1043","population":"3210","male":"1630","female":"1580","under15":"339","be1564":"2481","up65":"390","up20":"2650","be1819":"85"},"2017-08":{"households":"1045","population":"3227","male":"1636","female":"1591","under15":"341","be1564":"2492","up65":"394","up20":"2664","be1819":"88"},"2017-09":{"households":"1046","population":"3217","male":"1634","female":"1583","under15":"338","be1564":"2484","up65":"395","up20":"2662","be1819":"85"},"2017-10":{"households":"1047","population":"3225","male":"1634","female":"1591","under15":"339","be1564":"2485","up65":"401","up20":"2665","be1819":"87"},"2017-11":{"households":"1051","population":"3224","male":"1635","female":"1589","under15":"336","be1564":"2484","up65":"404","up20":"2665","be1819":"92"},"2017-12":{"households":"1052","population":"3231","male":"1636","female":"1595","under15":"333","be1564":"2494","up65":"404","up20":"2672","be1819":"95"}}}