{"code":"65000110-046","population":{"2018-03":{"households":"1818","population":"4680","male":"2309","female":"2371","under15":"643","be1564":"3512","up65":"525","up20":"3707","be1819":"142"},"2018-02":{"households":"1819","population":"4671","male":"2304","female":"2367","under15":"643","be1564":"3510","up65":"518","up20":"3701","be1819":"139"},"2018-01":{"households":"1820","population":"4671","male":"2303","female":"2368","under15":"643","be1564":"3512","up65":"516","up20":"3703","be1819":"140"},"2017-12":{"households":"1820","population":"4674","male":"2301","female":"2373","under15":"646","be1564":"3512","up65":"516","up20":"3702","be1819":"139"},"2017-11":{"households":"1823","population":"4675","male":"2306","female":"2369","under15":"647","be1564":"3515","up65":"513","up20":"3696","be1819":"145"},"2017-10":{"households":"1821","population":"4672","male":"2306","female":"2366","under15":"652","be1564":"3507","up65":"513","up20":"3689","be1819":"148"},"2017-09":{"households":"1818","population":"4660","male":"2296","female":"2364","under15":"649","be1564":"3502","up65":"509","up20":"3672","be1819":"152"},"2017-08":{"households":"1811","population":"4657","male":"2295","female":"2362","under15":"649","be1564":"3506","up65":"502","up20":"3659","be1819":"155"},"2017-07":{"households":"1810","population":"4662","male":"2294","female":"2368","under15":"653","be1564":"3511","up65":"498","up20":"3660","be1819":"154"},"2017-06":{"households":"1813","population":"4667","male":"2298","female":"2369","under15":"659","be1564":"3510","up65":"498","up20":"3653","be1819":"154"},"2017-05":{"households":"1807","population":"4652","male":"2289","female":"2363","under15":"661","be1564":"3501","up65":"490","up20":"3640","be1819":"150"},"2017-04":{"households":"1801","population":"4650","male":"2286","female":"2364","under15":"659","be1564":"3504","up65":"487","up20":"3638","be1819":"149"},"2017-03":{"households":"1797","population":"4630","male":"2281","female":"2349","under15":"648","be1564":"3498","up65":"484","up20":"3630","be1819":"142"},"2017-02":{"households":"1801","population":"4625","male":"2282","female":"2343","under15":"648","be1564":"3496","up65":"481","up20":"3622","be1819":"142"},"2017-01":{"households":"1802","population":"4614","male":"2277","female":"2337","under15":"644","be1564":"3494","up65":"476","up20":"3616","be1819":"144"},"2016-12":{"households":"1801","population":"4609","male":"2274","female":"2335","under15":"645","be1564":"3489","up65":"475","up20":"3609","be1819":"148"},"2016-11":{"households":"1806","population":"4631","male":"2285","female":"2346","under15":"652","be1564":"3506","up65":"473","up20":"3623","be1819":"147"},"2016-10":{"households":"1809","population":"4633","male":"2281","female":"2352","under15":"658","be1564":"3505","up65":"470","up20":"3629","be1819":"144"},"2016-09":{"households":"1811","population":"4627","male":"2279","female":"2348","under15":"660","be1564":"3499","up65":"468","up20":"3626","be1819":"141"},"2016-08":{"households":"1813","population":"4643","male":"2288","female":"2355","under15":"663","be1564":"3516","up65":"464","up20":"3633","be1819":"144"},"2016-07":{"households":"1810","population":"4644","male":"2294","female":"2350","under15":"666","be1564":"3514","up65":"464","up20":"3633","be1819":"143"},"2016-06":{"households":"1808","population":"4626","male":"2278","female":"2348","under15":"664","be1564":"3505","up65":"457","up20":"3619","be1819":"146"},"2016-05":{"households":"1807","population":"4616","male":"2277","female":"2339","under15":"659","be1564":"3503","up65":"454","up20":"3616","be1819":"141"},"2016-04":{"households":"1812","population":"4632","male":"2282","female":"2350","under15":"659","be1564":"3517","up65":"456","up20":"3622","be1819":"145"},"2016-03":{"households":"1817","population":"4638","male":"2289","female":"2349","under15":"661","be1564":"3518","up65":"459","up20":"3622","be1819":"146"},"2016-02":{"households":"1815","population":"4645","male":"2292","female":"2353","under15":"667","be1564":"3518","up65":"460","up20":"3619","be1819":"149"},"2016-01":{"households":"1816","population":"4639","male":"2279","female":"2360","under15":"667","be1564":"3518","up65":"454","up20":"3610","be1819":"153"},"2015-12":{"households":"1818","population":"4646","male":"2285","female":"2361","under15":"674","be1564":"3519","up65":"453","up20":"3606","be1819":"155"},"2015-11":{"households":"1820","population":"4636","male":"2281","female":"2355","under15":"677","be1564":"3513","up65":"446","up20":"3600","be1819":"151"},"2015-10":{"households":"1825","population":"4640","male":"2283","female":"2357","under15":"679","be1564":"3520","up65":"441","up20":"3600","be1819":"152"},"2015-09":{"households":"1826","population":"4638","male":"2289","female":"2349","under15":"681","be1564":"3522","up65":"435","up20":"3591","be1819":"149"},"2015-08":{"households":"1819","population":"4629","male":"2286","female":"2343","under15":"680","be1564":"3512","up65":"437","up20":"3585","be1819":"148"},"2015-07":{"households":"1819","population":"4640","male":"2293","female":"2347","under15":"686","be1564":"3517","up65":"437","up20":"3587","be1819":"149"},"2015-06":{"households":"1817","population":"4631","male":"2284","female":"2347","under15":"688","be1564":"3512","up65":"431","up20":"3577","be1819":"146"},"2015-05":{"households":"1818","population":"4614","male":"2284","female":"2330","under15":"690","be1564":"3493","up65":"431","up20":"3564","be1819":"144"},"2015-04":{"households":"1815","population":"4620","male":"2287","female":"2333","under15":"691","be1564":"3497","up65":"432","up20":"3566","be1819":"146"},"2015-03":{"households":"1816","population":"4621","male":"2289","female":"2332","under15":"691","be1564":"3501","up65":"429","up20":"3566","be1819":"150"},"2015-02":{"households":"1809","population":"4604","male":"2276","female":"2328","under15":"689","be1564":"3488","up65":"427","up20":"3552","be1819":"145"},"2015-01":{"households":"1807","population":"4591","male":"2268","female":"2323","under15":"692","be1564":"3475","up65":"424","up20":"3538","be1819":"144"},"2014-12":{"households":"1811","population":"4609","male":"2275","female":"2334","under15":"702","be1564":"3486","up65":"421","up20":"3548","be1819":"141"},"2014-11":{"households":"1809","population":"4613","male":"2268","female":"2345","under15":"696","be1564":"3502","up65":"415","up20":"3556","be1819":"144"},"2014-10":{"households":"1812","population":"4620","male":"2267","female":"2353","under15":"695","be1564":"3514","up65":"411","up20":"3563","be1819":"144"},"2014-09":{"households":"1814","population":"4634","male":"2277","female":"2357","under15":"700","be1564":"3525","up65":"409","up20":"3567","be1819":"146"},"2014-08":{"households":"1806","population":"4620","male":"2266","female":"2354","under15":"699","be1564":"3520","up65":"401","up20":"3554","be1819":"144"},"2014-07":{"households":"1801","population":"4610","male":"2262","female":"2348","under15":"690","be1564":"3520","up65":"400","up20":"3546","be1819":"145"},"2014-06":{"households":"1791","population":"4598","male":"2256","female":"2342","under15":"698","be1564":"3505","up65":"395","up20":"3532","be1819":"142"},"2014-05":{"households":"1793","population":"4619","male":"2260","female":"2359","under15":"710","be1564":"3515","up65":"394","up20":"3544","be1819":"145"},"2014-04":{"households":"1796","population":"4622","male":"2258","female":"2364","under15":"720","be1564":"3511","up65":"391","up20":"3541","be1819":"138"}}}