{"code":"65000110-022","population":{"2018-02":{"households":"2102","population":"4648","male":"2290","female":"2358","under15":"324","be1564":"3549","up65":"775","up20":"4144","be1819":"75"},"2018-01":{"households":"2103","population":"4634","male":"2280","female":"2354","under15":"322","be1564":"3543","up65":"769","up20":"4129","be1819":"80"},"2017-12":{"households":"2096","population":"4615","male":"2270","female":"2345","under15":"315","be1564":"3535","up65":"765","up20":"4113","be1819":"80"},"2017-11":{"households":"2091","population":"4604","male":"2262","female":"2342","under15":"316","be1564":"3527","up65":"761","up20":"4097","be1819":"82"},"2017-10":{"households":"2094","population":"4607","male":"2266","female":"2341","under15":"317","be1564":"3534","up65":"756","up20":"4097","be1819":"85"},"2017-09":{"households":"2095","population":"4603","male":"2266","female":"2337","under15":"312","be1564":"3539","up65":"752","up20":"4095","be1819":"89"},"2017-08":{"households":"2095","population":"4611","male":"2265","female":"2346","under15":"314","be1564":"3552","up65":"745","up20":"4101","be1819":"84"},"2017-07":{"households":"2095","population":"4617","male":"2264","female":"2353","under15":"316","be1564":"3558","up65":"743","up20":"4105","be1819":"84"},"2017-06":{"households":"2099","population":"4617","male":"2266","female":"2351","under15":"321","be1564":"3554","up65":"742","up20":"4099","be1819":"87"},"2017-05":{"households":"2099","population":"4612","male":"2264","female":"2348","under15":"323","be1564":"3553","up65":"736","up20":"4094","be1819":"85"},"2017-04":{"households":"2088","population":"4619","male":"2263","female":"2356","under15":"333","be1564":"3554","up65":"732","up20":"4089","be1819":"84"},"2017-03":{"households":"2095","population":"4635","male":"2266","female":"2369","under15":"337","be1564":"3567","up65":"731","up20":"4095","be1819":"86"},"2017-02":{"households":"2090","population":"4622","male":"2257","female":"2365","under15":"335","be1564":"3566","up65":"721","up20":"4085","be1819":"85"},"2017-01":{"households":"2091","population":"4599","male":"2242","female":"2357","under15":"325","be1564":"3562","up65":"712","up20":"4072","be1819":"83"},"2016-12":{"households":"2091","population":"4587","male":"2239","female":"2348","under15":"323","be1564":"3560","up65":"704","up20":"4065","be1819":"82"},"2016-11":{"households":"2092","population":"4605","male":"2243","female":"2362","under15":"332","be1564":"3567","up65":"706","up20":"4073","be1819":"82"},"2016-10":{"households":"2081","population":"4591","male":"2239","female":"2352","under15":"331","be1564":"3565","up65":"695","up20":"4058","be1819":"83"},"2016-09":{"households":"2078","population":"4577","male":"2238","female":"2339","under15":"328","be1564":"3562","up65":"687","up20":"4050","be1819":"82"},"2016-08":{"households":"2075","population":"4565","male":"2230","female":"2335","under15":"328","be1564":"3553","up65":"684","up20":"4041","be1819":"83"},"2016-07":{"households":"2075","population":"4564","male":"2237","female":"2327","under15":"335","be1564":"3547","up65":"682","up20":"4032","be1819":"85"},"2016-06":{"households":"2073","population":"4567","male":"2243","female":"2324","under15":"333","be1564":"3552","up65":"682","up20":"4034","be1819":"91"},"2016-05":{"households":"2078","population":"4579","male":"2253","female":"2326","under15":"340","be1564":"3556","up65":"683","up20":"4038","be1819":"95"},"2016-04":{"households":"2074","population":"4582","male":"2253","female":"2329","under15":"340","be1564":"3562","up65":"680","up20":"4039","be1819":"95"},"2016-03":{"households":"2079","population":"4593","male":"2261","female":"2332","under15":"346","be1564":"3573","up65":"674","up20":"4040","be1819":"96"},"2016-02":{"households":"2071","population":"4590","male":"2261","female":"2329","under15":"342","be1564":"3578","up65":"670","up20":"4035","be1819":"98"},"2016-01":{"households":"2076","population":"4608","male":"2272","female":"2336","under15":"343","be1564":"3596","up65":"669","up20":"4047","be1819":"99"},"2015-12":{"households":"2078","population":"4612","male":"2275","female":"2337","under15":"345","be1564":"3608","up65":"659","up20":"4048","be1819":"98"},"2015-11":{"households":"2082","population":"4617","male":"2276","female":"2341","under15":"350","be1564":"3611","up65":"656","up20":"4047","be1819":"97"},"2015-10":{"households":"2079","population":"4616","male":"2274","female":"2342","under15":"351","be1564":"3611","up65":"654","up20":"4052","be1819":"91"},"2015-09":{"households":"2086","population":"4618","male":"2271","female":"2347","under15":"349","be1564":"3621","up65":"648","up20":"4049","be1819":"96"},"2015-08":{"households":"2085","population":"4626","male":"2273","female":"2353","under15":"353","be1564":"3631","up65":"642","up20":"4045","be1819":"107"},"2015-07":{"households":"2084","population":"4620","male":"2271","female":"2349","under15":"352","be1564":"3627","up65":"641","up20":"4042","be1819":"101"},"2015-06":{"households":"2088","population":"4622","male":"2276","female":"2346","under15":"354","be1564":"3629","up65":"639","up20":"4043","be1819":"100"},"2015-05":{"households":"2092","population":"4637","male":"2284","female":"2353","under15":"361","be1564":"3635","up65":"641","up20":"4050","be1819":"104"},"2015-04":{"households":"2094","population":"4638","male":"2288","female":"2350","under15":"358","be1564":"3639","up65":"641","up20":"4050","be1819":"108"},"2015-03":{"households":"2096","population":"4651","male":"2293","female":"2358","under15":"365","be1564":"3647","up65":"639","up20":"4060","be1819":"108"},"2015-02":{"households":"2092","population":"4656","male":"2298","female":"2358","under15":"367","be1564":"3653","up65":"636","up20":"4060","be1819":"111"},"2015-01":{"households":"2095","population":"4653","male":"2301","female":"2352","under15":"361","be1564":"3656","up65":"636","up20":"4056","be1819":"116"},"2014-12":{"households":"2096","population":"4659","male":"2308","female":"2351","under15":"371","be1564":"3652","up65":"636","up20":"4061","be1819":"114"},"2014-11":{"households":"2102","population":"4656","male":"2311","female":"2345","under15":"367","be1564":"3652","up65":"637","up20":"4062","be1819":"115"},"2014-10":{"households":"2104","population":"4666","male":"2314","female":"2352","under15":"370","be1564":"3658","up65":"638","up20":"4066","be1819":"115"},"2014-09":{"households":"2102","population":"4665","male":"2314","female":"2351","under15":"363","be1564":"3669","up65":"633","up20":"4070","be1819":"118"},"2014-08":{"households":"2100","population":"4679","male":"2318","female":"2361","under15":"370","be1564":"3677","up65":"632","up20":"4080","be1819":"119"},"2014-07":{"households":"2092","population":"4668","male":"2310","female":"2358","under15":"368","be1564":"3677","up65":"623","up20":"4067","be1819":"118"},"2014-06":{"households":"2093","population":"4685","male":"2315","female":"2370","under15":"374","be1564":"3683","up65":"628","up20":"4075","be1819":"120"},"2014-05":{"households":"2094","population":"4701","male":"2325","female":"2376","under15":"379","be1564":"3692","up65":"630","up20":"4079","be1819":"127"},"2014-04":{"households":"2087","population":"4693","male":"2321","female":"2372","under15":"379","be1564":"3687","up65":"627","up20":"4077","be1819":"122"}}}